{
  "projects": {
    "zoom-extraction": {
      "health": "healthy",
      "message": "Extracted 0 sessions",
      "lastCheck": "2026-01-08T04:30:15Z",
      "lastSuccess": "2026-01-08T04:30:15Z"
    },
    "pre-sales": {
      "health": "healthy",
      "message": "Sync service running",
      "lastCheck": "2026-01-08T18:00:03Z",
      "lastSuccess": "2026-01-08T18:00:03Z"
    },
    "pv-reviews": {
      "health": "healthy",
      "message": "Weekly posting completed",
      "lastCheck": "2026-01-08T16:30:06Z",
      "lastSuccess": "2026-01-08T16:30:06Z"
    },
    "post-sales": {
      "health": "healthy",
      "message": "OK",
      "lastCheck": "2026-01-08T17:32:12.359745Z",
      "lastSuccess": "2026-01-08T17:32:12.359745Z"
    },
    "ei-ats": {
      "health": "healthy",
      "message": "OK",
      "lastCheck": "2026-01-08T17:32:12.359745Z",
      "lastSuccess": "2026-01-08T17:32:12.359745Z"
    },
    "gsp26-chatbot": {
      "health": "healthy",
      "message": "OK",
      "lastCheck": "2026-01-08T17:32:12.359745Z",
      "lastSuccess": "2026-01-08T17:32:12.359745Z"
    },
    "resume-screening": {
      "health": "healthy",
      "message": "OK",
      "lastCheck": "2026-01-08T17:32:12.359745Z",
      "lastSuccess": "2026-01-08T17:32:12.359745Z"
    },
    "teacherhire-demo": {
      "health": "healthy",
      "message": "OK",
      "lastCheck": "2026-01-08T17:32:12.359745Z",
      "lastSuccess": "2026-01-08T17:32:12.359745Z"
    },
    "websites": {
      "health": "healthy",
      "message": "OK",
      "lastCheck": "2026-01-08T17:32:12.359745Z",
      "lastSuccess": "2026-01-08T17:32:12.359745Z"
    },
    "mycliniq": {
      "health": "healthy",
      "message": "OK",
      "lastCheck": "2026-01-08T17:32:12.359745Z",
      "lastSuccess": "2026-01-08T17:32:12.359745Z"
    },
    "clubgw": {
      "health": "healthy",
      "message": "OK",
      "lastCheck": "2026-01-08T17:32:12.359745Z",
      "lastSuccess": "2026-01-08T17:32:12.359745Z"
    },
    "youtube-mcp": {
      "health": "healthy",
      "message": "MCP server ready",
      "lastCheck": "2026-01-07T10:00:00Z",
      "lastSuccess": "2026-01-07T10:00:00Z"
    },
    "chimplyfun": {
      "health": "healthy",
      "message": "OK",
      "lastCheck": "2026-01-08T17:32:12.359745Z",
      "lastSuccess": "2026-01-08T17:32:12.359745Z"
    },
    "bridge": {
      "health": "healthy",
      "message": "Local dev ready",
      "lastCheck": "2026-01-07T10:00:00Z",
      "lastSuccess": "2026-01-07T10:00:00Z"
    },
    "devcommandcenter": {
      "health": "healthy",
      "message": "OK",
      "lastCheck": "2026-01-08T17:32:12.359745Z",
      "lastSuccess": "2026-01-08T17:32:12.359745Z"
    },
    "whatsapp-workflows": {
      "health": "healthy",
      "message": "Workflows ready",
      "lastCheck": "2026-01-07T10:00:00Z",
      "lastSuccess": "2026-01-07T10:00:00Z"
    },
    "social-media-posts": {
      "health": "healthy",
      "message": "Tracking active",
      "lastCheck": "2026-01-07T10:00:00Z",
      "lastSuccess": "2026-01-07T10:00:00Z"
    },
    "faces": {
      "health": "healthy",
      "message": "Local tool ready",
      "lastCheck": "2026-01-07T10:00:00Z",
      "lastSuccess": "2026-01-07T10:00:00Z"
    },
    "obsidian": {
      "health": "healthy",
      "message": "Integration ready",
      "lastCheck": "2026-01-07T10:00:00Z",
      "lastSuccess": "2026-01-07T10:00:00Z"
    },
    "skch": {
      "health": "healthy",
      "message": "Archive complete",
      "lastCheck": "2026-01-07T10:00:00Z",
      "lastSuccess": "2026-01-07T10:00:00Z"
    },
    "schoolname": {
      "health": "healthy",
      "message": "Mapping complete",
      "lastCheck": "2026-01-07T10:00:00Z",
      "lastSuccess": "2026-01-07T10:00:00Z"
    }
  },
  "lastUpdated": "2026-01-08T18:00:03Z"
}